seldegen/.DS_Store
seldegen/__init__.py
seldegen/abc/__init__.py
seldegen/abc/base_account.py
seldegen/abc/browser_extension.py
seldegen/abc/dapp.py
seldegen/abc/wallet.py
seldegen/captcha_solver.py
seldegen/captcha_waiter.py
seldegen/context.py
seldegen/dapps/__init__.py
seldegen/dapps/guild.py
seldegen/dapps/lens.py
seldegen/dapps/snapshot.py
seldegen/email.py
seldegen/exceptions.py
seldegen/extensions/__init__.py
seldegen/extensions/authenticator.py
seldegen/extensions/capmonster.py
seldegen/globals.py
seldegen/socials/__init__.py
seldegen/socials/discord.py
seldegen/socials/facebook.py
seldegen/socials/github.py
seldegen/socials/gmail.py
seldegen/socials/google.py
seldegen/socials/linkedin.py
seldegen/socials/twitter.py
seldegen/types.py
seldegen/wallets/__init__.py
seldegen/wallets/metamask.py
seldegen/wallets/sui_wallet.py
seldegen-0.1.4.post3.dist-info/LICENSE
seldegen-0.1.4.post3.dist-info/METADATA
seldegen-0.1.4.post3.dist-info/WHEEL
seldegen-0.1.4.post3.dist-info/RECORD
