Metadata-Version: 2.1
Name: seldegen
Version: 0.1.4.post3
Summary: The package containing tools to warm up Web3-based project using Selenium
Home-page: https://github.com/CrocoFactory/seldegen
License: MIT
Author: Alexey
Author-email: axbelenkov@gmail.com
Requires-Python: >=3.11,<4.0
Classifier: Development Status :: 4 - Beta
Classifier: Intended Audience :: Developers
Classifier: License :: OSI Approved :: MIT License
Classifier: Operating System :: MacOS
Classifier: Operating System :: Microsoft :: Windows
Classifier: Programming Language :: Python :: 3
Classifier: Programming Language :: Python :: 3.11
Classifier: Programming Language :: Python :: 3.12
Classifier: Programming Language :: Python :: 3 :: Only
Classifier: Topic :: Software Development :: Libraries :: Python Modules
Requires-Dist: 2captcha-python (>=1.2.2,<2.0.0)
Requires-Dist: croco-selenium (>=0.1.6,<0.2.0)
Requires-Dist: eth-account (>=0.11.0,<0.12.0)
Requires-Dist: faker (>=24.3.0,<25.0.0)
Requires-Dist: imap-tools (>=1.5.0,<2.0.0)
Requires-Dist: pyotp (>=2.9.0,<3.0.0)
Requires-Dist: pyperclip (>=1.8.2,<2.0.0)
Requires-Dist: selenium (>=4.16.0,<5.0.0)
Project-URL: Repository, https://github.com/CrocoFactory/seldegen
